Metadata-Version: 1.0
Name: words-counter
Version: 1.3.7
Summary: UNKNOWN
Home-page: https://github.com/Ranc58/verbs_counter
Author: Vladimir Aleshin
Author-email: rancvova@gmail.com
License: MIT License
Platform: UNKNOWN
